[{"i":0,"j":0,"value":0.09803921568627451},{"i":0,"j":1,"value":0.0},{"i":0,"j":2,"value":0.0},{"i":0,"j":3,"value":0.0},{"i":0,"j":4,"value":0.0},{"i":0,"j":5,"value":0.0},{"i":0,"j":6,"value":0.0},{"i":0,"j":7,"value":0.0},{"i":0,"j":8,"value":0.0},{"i":0,"j":9,"value":0.0},{"i":0,"j":10,"value":0.0},{"i":0,"j":11,"value":0.0},{"i":0,"j":12,"value":0.0},{"i":0,"j":13,"value":0.0},{"i":0,"j":14,"value":0.0},{"i":0,"j":15,"value":0.0},{"i":0,"j":16,"value":0.01960784313725489},{"i":0,"j":17,"value":0.0},{"i":0,"j":18,"value":0.0},{"i":0,"j":19,"value":0.0},{"i":0,"j":20,"value":0.0},{"i":0,"j":21,"value":0.0},{"i":0,"j":22,"value":0.0},{"i":0,"j":23,"value":0.0},{"i":0,"j":24,"value":0.019607843137254898},{"i":0,"j":25,"value":0.0},{"i":0,"j":26,"value":0.0},{"i":0,"j":27,"value":0.0},{"i":0,"j":28,"value":0.01960784313725491},{"i":0,"j":29,"value":0.01960784313725491},{"i":0,"j":30,"value":0.0},{"i":0,"j":31,"value":0.0},{"i":0,"j":32,"value":0.0},{"i":0,"j":33,"value":0.0},{"i":0,"j":34,"value":0.0},{"i":0,"j":35,"value":0.0},{"i":0,"j":36,"value":0.0},{"i":0,"j":37,"value":0.0},{"i":0,"j":38,"value":0.0},{"i":0,"j":39,"value":0.0},{"i":0,"j":40,"value":0.0},{"i":0,"j":41,"value":0.0},{"i":0,"j":42,"value":0.0},{"i":0,"j":43,"value":0.0},{"i":0,"j":44,"value":0.0},{"i":0,"j":45,"value":0.0},{"i":0,"j":46,"value":0.0},{"i":0,"j":47,"value":0.0},{"i":0,"j":48,"value":0.0},{"i":0,"j":49,"value":0.0},{"i":0,"j":50,"value":0.0},{"i":0,"j":51,"value":0.0},{"i":0,"j":52,"value":0.0},{"i":0,"j":53,"value":0.0},{"i":0,"j":54,"value":0.0},{"i":0,"j":55,"value":0.0},{"i":0,"j":56,"value":0.0},{"i":0,"j":57,"value":0.0},{"i":0,"j":58,"value":0.0},{"i":0,"j":59,"value":0.0},{"i":0,"j":60,"value":0.019607843137254895},{"i":0,"j":61,"value":0.0},{"i":0,"j":62,"value":0.0},{"i":0,"j":63,"value":0.0},{"i":0,"j":64,"value":0.0},{"i":0,"j":65,"value":0.03921568627450978},{"i":0,"j":66,"value":0.0},{"i":0,"j":67,"value":0.15686274509803916},{"i":0,"j":68,"value":0.0},{"i":0,"j":69,"value":0.019607843137254895},{"i":0,"j":70,"value":0.0},{"i":0,"j":71,"value":0.0},{"i":0,"j":72,"value":0.0},{"i":0,"j":73,"value":0.0},{"i":0,"j":74,"value":0.0},{"i":0,"j":75,"value":0.019607843137254895},{"i":0,"j":76,"value":0.0},{"i":0,"j":77,"value":0.0},{"i":0,"j":78,"value":0.0},{"i":0,"j":79,"value":0.0},{"i":0,"j":80,"value":0.0},{"i":0,"j":81,"value":0.0},{"i":0,"j":82,"value":0.01960784313725491},{"i":0,"j":83,"value":0.1764705882352941},{"i":0,"j":84,"value":0.0},{"i":0,"j":85,"value":0.03921568627450979},{"i":0,"j":86,"value":0.0},{"i":0,"j":87,"value":0.0},{"i":0,"j":88,"value":0.0},{"i":0,"j":89,"value":0.0},{"i":0,"j":90,"value":0.019607843137254895},{"i":0,"j":91,"value":0.0},{"i":0,"j":92,"value":0.0},{"i":0,"j":93,"value":0.0},{"i":0,"j":94,"value":0.0},{"i":0,"j":95,"value":0.0},{"i":0,"j":96,"value":0.0},{"i":0,"j":97,"value":0.0},{"i":0,"j":98,"value":0.0},{"i":0,"j":99,"value":0.0},{"i":0,"j":100,"value":0.0784313725490196},{"i":0,"j":101,"value":0.01960784313725491},{"i":0,"j":102,"value":0.0},{"i":0,"j":103,"value":0.0},{"i":0,"j":104,"value":0.0},{"i":0,"j":105,"value":0.01960784313725489},{"i":0,"j":106,"value":0.0},{"i":0,"j":107,"value":0.0},{"i":0,"j":108,"value":0.0},{"i":0,"j":109,"value":0.0},{"i":0,"j":110,"value":0.0},{"i":0,"j":111,"value":0.0},{"i":0,"j":112,"value":0.0},{"i":0,"j":113,"value":0.0},{"i":0,"j":114,"value":0.0},{"i":0,"j":115,"value":0.0},{"i":0,"j":116,"value":0.0},{"i":0,"j":117,"value":0.0},{"i":0,"j":118,"value":0.0},{"i":0,"j":119,"value":0.0},{"i":0,"j":120,"value":0.0},{"i":0,"j":121,"value":0.0},{"i":0,"j":122,"value":0.0},{"i":0,"j":123,"value":0.0},{"i":0,"j":124,"value":0.0},{"i":0,"j":125,"value":0.019607843137254895},{"i":0,"j":126,"value":0.0},{"i":0,"j":127,"value":0.0},{"i":0,"j":128,"value":0.0},{"i":0,"j":129,"value":0.0},{"i":0,"j":130,"value":0.0},{"i":0,"j":131,"value":0.0},{"i":0,"j":132,"value":0.0},{"i":0,"j":133,"value":0.0},{"i":0,"j":134,"value":0.0},{"i":0,"j":135,"value":0.0},{"i":0,"j":136,"value":0.0},{"i":0,"j":137,"value":0.0},{"i":0,"j":138,"value":0.0},{"i":0,"j":139,"value":0.0},{"i":0,"j":140,"value":0.0},{"i":0,"j":141,"value":0.0},{"i":0,"j":142,"value":0.0},{"i":0,"j":143,"value":0.0},{"i":0,"j":144,"value":0.0},{"i":0,"j":145,"value":0.0},{"i":0,"j":146,"value":0.0},{"i":0,"j":147,"value":0.0},{"i":0,"j":148,"value":0.0},{"i":0,"j":149,"value":0.0},{"i":0,"j":150,"value":0.01960784313725491},{"i":0,"j":151,"value":0.019607843137254898},{"i":0,"j":152,"value":0.0},{"i":0,"j":153,"value":0.0},{"i":0,"j":154,"value":0.0},{"i":0,"j":155,"value":0.0},{"i":0,"j":156,"value":0.0},{"i":0,"j":157,"value":0.0},{"i":0,"j":158,"value":0.0},{"i":0,"j":159,"value":0.0},{"i":0,"j":160,"value":0.01960784313725491},{"i":0,"j":161,"value":0.0},{"i":0,"j":162,"value":0.0},{"i":0,"j":163,"value":0.0},{"i":0,"j":164,"value":0.0},{"i":0,"j":165,"value":0.0},{"i":0,"j":166,"value":0.0},{"i":0,"j":167,"value":0.0},{"i":0,"j":168,"value":0.0},{"i":0,"j":169,"value":0.0},{"i":0,"j":170,"value":0.0},{"i":0,"j":171,"value":0.0},{"i":0,"j":172,"value":0.0},{"i":0,"j":173,"value":0.0},{"i":0,"j":174,"value":0.0},{"i":0,"j":175,"value":0.0},{"i":0,"j":176,"value":0.0},{"i":0,"j":177,"value":0.0},{"i":0,"j":178,"value":0.0},{"i":0,"j":179,"value":0.0},{"i":0,"j":180,"value":0.0},{"i":0,"j":181,"value":0.0},{"i":0,"j":182,"value":0.0},{"i":0,"j":183,"value":0.0},{"i":0,"j":184,"value":0.0},{"i":0,"j":185,"value":0.0},{"i":0,"j":186,"value":0.0},{"i":0,"j":187,"value":0.0},{"i":0,"j":188,"value":0.0},{"i":0,"j":189,"value":0.0},{"i":0,"j":190,"value":0.0},{"i":0,"j":191,"value":0.0},{"i":0,"j":192,"value":0.0},{"i":0,"j":193,"value":0.0},{"i":0,"j":194,"value":0.0},{"i":0,"j":195,"value":0.0},{"i":0,"j":196,"value":0.0},{"i":0,"j":197,"value":0.0},{"i":0,"j":198,"value":0.0},{"i":0,"j":199,"value":0.0},{"i":0,"j":200,"value":0.019607843137254895},{"i":0,"j":201,"value":0.0},{"i":0,"j":202,"value":0.0},{"i":0,"j":203,"value":0.0},{"i":0,"j":204,"value":0.0},{"i":0,"j":205,"value":0.0},{"i":0,"j":206,"value":0.0},{"i":0,"j":207,"value":0.0},{"i":0,"j":208,"value":0.0},{"i":0,"j":209,"value":0.0},{"i":0,"j":210,"value":0.0},{"i":0,"j":211,"value":0.0},{"i":0,"j":212,"value":0.0},{"i":0,"j":213,"value":0.0},{"i":0,"j":214,"value":0.0},{"i":0,"j":215,"value":0.0},{"i":0,"j":216,"value":0.0},{"i":0,"j":217,"value":0.0},{"i":0,"j":218,"value":0.01960784313725491},{"i":0,"j":219,"value":0.0},{"i":0,"j":220,"value":0.0},{"i":0,"j":221,"value":0.0},{"i":0,"j":222,"value":0.0},{"i":0,"j":223,"value":0.0},{"i":0,"j":224,"value":0.0},{"i":0,"j":225,"value":0.0},{"i":0,"j":226,"value":0.0},{"i":0,"j":227,"value":0.0},{"i":0,"j":228,"value":0.0},{"i":0,"j":229,"value":0.0},{"i":0,"j":230,"value":0.0},{"i":0,"j":231,"value":0.0},{"i":0,"j":232,"value":0.0},{"i":0,"j":233,"value":0.0},{"i":0,"j":234,"value":0.0},{"i":0,"j":235,"value":0.0},{"i":0,"j":236,"value":0.0},{"i":0,"j":237,"value":0.0},{"i":0,"j":238,"value":0.0},{"i":0,"j":239,"value":0.0},{"i":0,"j":240,"value":0.0},{"i":0,"j":241,"value":0.0},{"i":0,"j":242,"value":0.0},{"i":0,"j":243,"value":0.0},{"i":0,"j":244,"value":0.0},{"i":0,"j":245,"value":0.0},{"i":0,"j":246,"value":0.0},{"i":0,"j":247,"value":0.0},{"i":0,"j":248,"value":0.0},{"i":0,"j":249,"value":0.0},{"i":0,"j":250,"value":0.0},{"i":0,"j":251,"value":0.0},{"i":0,"j":252,"value":0.0},{"i":0,"j":253,"value":0.0},{"i":0,"j":254,"value":0.03921568627450979},{"i":0,"j":255,"value":0.03921568627450979},{"i":1,"j":0,"value":0.07843137254901958},{"i":1,"j":1,"value":0.01960784313725491},{"i":1,"j":2,"value":0.0},{"i":1,"j":3,"value":0.0},{"i":1,"j":4,"value":0.0},{"i":1,"j":5,"value":0.01960784313725489},{"i":1,"j":6,"value":0.0},{"i":1,"j":7,"value":0.0},{"i":1,"j":8,"value":0.0},{"i":1,"j":9,"value":0.0},{"i":1,"j":10,"value":0.0},{"i":1,"j":11,"value":0.0},{"i":1,"j":12,"value":0.0},{"i":1,"j":13,"value":0.0},{"i":1,"j":14,"value":0.0},{"i":1,"j":15,"value":0.0},{"i":1,"j":16,"value":0.0},{"i":1,"j":17,"value":0.0},{"i":1,"j":18,"value":0.0},{"i":1,"j":19,"value":0.0},{"i":1,"j":20,"value":0.0},{"i":1,"j":21,"value":0.0},{"i":1,"j":22,"value":0.0},{"i":1,"j":23,"value":0.0},{"i":1,"j":24,"value":0.019607843137254898},{"i":1,"j":25,"value":0.0},{"i":1,"j":26,"value":0.0},{"i":1,"j":27,"value":0.0},{"i":1,"j":28,"value":0.0},{"i":1,"j":29,"value":0.0},{"i":1,"j":30,"value":0.0},{"i":1,"j":31,"value":0.0},{"i":1,"j":32,"value":0.01960784313725491},{"i":1,"j":33,"value":0.0},{"i":1,"j":34,"value":0.0},{"i":1,"j":35,"value":0.0},{"i":1,"j":36,"value":0.0},{"i":1,"j":37,"value":0.0},{"i":1,"j":38,"value":0.0},{"i":1,"j":39,"value":0.0},{"i":1,"j":40,"value":0.0},{"i":1,"j":41,"value":0.0},{"i":1,"j":42,"value":0.0},{"i":1,"j":43,"value":0.0},{"i":1,"j":44,"value":0.0},{"i":1,"j":45,"value":0.01960784313725491},{"i":1,"j":46,"value":0.0},{"i":1,"j":47,"value":0.0},{"i":1,"j":48,"value":0.0},{"i":1,"j":49,"value":0.0},{"i":1,"j":50,"value":0.0},{"i":1,"j":51,"value":0.0},{"i":1,"j":52,"value":0.0},{"i":1,"j":53,"value":0.0},{"i":1,"j":54,"value":0.0},{"i":1,"j":55,"value":0.0},{"i":1,"j":56,"value":0.0},{"i":1,"j":57,"value":0.0},{"i":1,"j":58,"value":0.0},{"i":1,"j":59,"value":0.03921568627450979},{"i":1,"j":60,"value":0.0},{"i":1,"j":61,"value":0.0},{"i":1,"j":62,"value":0.0},{"i":1,"j":63,"value":0.0},{"i":1,"j":64,"value":0.0},{"i":1,"j":65,"value":0.0},{"i":1,"j":66,"value":0.0},{"i":1,"j":67,"value":0.0},{"i":1,"j":68,"value":0.15686274509803916},{"i":1,"j":69,"value":0.01960784313725491},{"i":1,"j":70,"value":0.0},{"i":1,"j":71,"value":0.0},{"i":1,"j":72,"value":0.019607843137254895},{"i":1,"j":73,"value":0.0784313725490196},{"i":1,"j":74,"value":0.0},{"i":1,"j":75,"value":0.0},{"i":1,"j":76,"value":0.0},{"i":1,"j":77,"value":0.019607843137254898},{"i":1,"j":78,"value":0.0},{"i":1,"j":79,"value":0.0},{"i":1,"j":80,"value":0.0},{"i":1,"j":81,"value":0.0},{"i":1,"j":82,"value":0.0784313725490196},{"i":1,"j":83,"value":0.0},{"i":1,"j":84,"value":0.0},{"i":1,"j":85,"value":0.03921568627450979},{"i":1,"j":86,"value":0.0},{"i":1,"j":87,"value":0.0},{"i":1,"j":88,"value":0.0},{"i":1,"j":89,"value":0.019607843137254895},{"i":1,"j":90,"value":0.0},{"i":1,"j":91,"value":0.0},{"i":1,"j":92,"value":0.0},{"i":1,"j":93,"value":0.0},{"i":1,"j":94,"value":0.0},{"i":1,"j":95,"value":0.0},{"i":1,"j":96,"value":0.0},{"i":1,"j":97,"value":0.0},{"i":1,"j":98,"value":0.0},{"i":1,"j":99,"value":0.03921568627450978},{"i":1,"j":100,"value":0.0},{"i":1,"j":101,"value":0.0},{"i":1,"j":102,"value":0.0},{"i":1,"j":103,"value":0.0},{"i":1,"j":104,"value":0.0},{"i":1,"j":105,"value":0.01960784313725491},{"i":1,"j":106,"value":0.0},{"i":1,"j":107,"value":0.0},{"i":1,"j":108,"value":0.0},{"i":1,"j":109,"value":0.0},{"i":1,"j":110,"value":0.0},{"i":1,"j":111,"value":0.058823529411764705},{"i":1,"j":112,"value":0.0},{"i":1,"j":113,"value":0.0},{"i":1,"j":114,"value":0.0},{"i":1,"j":115,"value":0.019607843137254895},{"i":1,"j":116,"value":0.01960784313725489},{"i":1,"j":117,"value":0.0},{"i":1,"j":118,"value":0.01960784313725491},{"i":1,"j":119,"value":0.0},{"i":1,"j":120,"value":0.0},{"i":1,"j":121,"value":0.0},{"i":1,"j":122,"value":0.0},{"i":1,"j":123,"value":0.0},{"i":1,"j":124,"value":0.0},{"i":1,"j":125,"value":0.0},{"i":1,"j":126,"value":0.0},{"i":1,"j":127,"value":0.0},{"i":1,"j":128,"value":0.0},{"i":1,"j":129,"value":0.0},{"i":1,"j":130,"value":0.0},{"i":1,"j":131,"value":0.0},{"i":1,"j":132,"value":0.0},{"i":1,"j":133,"value":0.0},{"i":1,"j":134,"value":0.0},{"i":1,"j":135,"value":0.0},{"i":1,"j":136,"value":0.0},{"i":1,"j":137,"value":0.0},{"i":1,"j":138,"value":0.0},{"i":1,"j":139,"value":0.0},{"i":1,"j":140,"value":0.0},{"i":1,"j":141,"value":0.0},{"i":1,"j":142,"value":0.0},{"i":1,"j":143,"value":0.0},{"i":1,"j":144,"value":0.0},{"i":1,"j":145,"value":0.0},{"i":1,"j":146,"value":0.0},{"i":1,"j":147,"value":0.0},{"i":1,"j":148,"value":0.0},{"i":1,"j":149,"value":0.0},{"i":1,"j":150,"value":0.0},{"i":1,"j":151,"value":0.019607843137254895},{"i":1,"j":152,"value":0.0},{"i":1,"j":153,"value":0.0},{"i":1,"j":154,"value":0.0},{"i":1,"j":155,"value":0.0},{"i":1,"j":156,"value":0.0},{"i":1,"j":157,"value":0.0},{"i":1,"j":158,"value":0.019607843137254895},{"i":1,"j":159,"value":0.0},{"i":1,"j":160,"value":0.0},{"i":1,"j":161,"value":0.0},{"i":1,"j":162,"value":0.0},{"i":1,"j":163,"value":0.0},{"i":1,"j":164,"value":0.0},{"i":1,"j":165,"value":0.0},{"i":1,"j":166,"value":0.0},{"i":1,"j":167,"value":0.0},{"i":1,"j":168,"value":0.0},{"i":1,"j":169,"value":0.0},{"i":1,"j":170,"value":0.0},{"i":1,"j":171,"value":0.0},{"i":1,"j":172,"value":0.0},{"i":1,"j":173,"value":0.0},{"i":1,"j":174,"value":0.0},{"i":1,"j":175,"value":0.0},{"i":1,"j":176,"value":0.0},{"i":1,"j":177,"value":0.0},{"i":1,"j":178,"value":0.0},{"i":1,"j":179,"value":0.0},{"i":1,"j":180,"value":0.0},{"i":1,"j":181,"value":0.0},{"i":1,"j":182,"value":0.0},{"i":1,"j":183,"value":0.0},{"i":1,"j":184,"value":0.0},{"i":1,"j":185,"value":0.0},{"i":1,"j":186,"value":0.0},{"i":1,"j":187,"value":0.0},{"i":1,"j":188,"value":0.0},{"i":1,"j":189,"value":0.0},{"i":1,"j":190,"value":0.0},{"i":1,"j":191,"value":0.0},{"i":1,"j":192,"value":0.0},{"i":1,"j":193,"value":0.0},{"i":1,"j":194,"value":0.0},{"i":1,"j":195,"value":0.0},{"i":1,"j":196,"value":0.0},{"i":1,"j":197,"value":0.0},{"i":1,"j":198,"value":0.01960784313725489},{"i":1,"j":199,"value":0.0},{"i":1,"j":200,"value":0.0},{"i":1,"j":201,"value":0.0},{"i":1,"j":202,"value":0.0},{"i":1,"j":203,"value":0.0},{"i":1,"j":204,"value":0.0},{"i":1,"j":205,"value":0.0},{"i":1,"j":206,"value":0.0},{"i":1,"j":207,"value":0.0},{"i":1,"j":208,"value":0.0},{"i":1,"j":209,"value":0.0},{"i":1,"j":210,"value":0.0},{"i":1,"j":211,"value":0.0},{"i":1,"j":212,"value":0.0},{"i":1,"j":213,"value":0.0},{"i":1,"j":214,"value":0.0},{"i":1,"j":215,"value":0.0},{"i":1,"j":216,"value":0.0},{"i":1,"j":217,"value":0.0},{"i":1,"j":218,"value":0.0},{"i":1,"j":219,"value":0.01960784313725489},{"i":1,"j":220,"value":0.0},{"i":1,"j":221,"value":0.0},{"i":1,"j":222,"value":0.0},{"i":1,"j":223,"value":0.0},{"i":1,"j":224,"value":0.0},{"i":1,"j":225,"value":0.0},{"i":1,"j":226,"value":0.0},{"i":1,"j":227,"value":0.03921568627450979},{"i":1,"j":228,"value":0.0},{"i":1,"j":229,"value":0.0},{"i":1,"j":230,"value":0.0},{"i":1,"j":231,"value":0.0},{"i":1,"j":232,"value":0.0},{"i":1,"j":233,"value":0.0},{"i":1,"j":234,"value":0.0},{"i":1,"j":235,"value":0.0},{"i":1,"j":236,"value":0.0},{"i":1,"j":237,"value":0.0},{"i":1,"j":238,"value":0.0},{"i":1,"j":239,"value":0.0},{"i":1,"j":240,"value":0.0},{"i":1,"j":241,"value":0.0},{"i":1,"j":242,"value":0.0},{"i":1,"j":243,"value":0.0},{"i":1,"j":244,"value":0.0},{"i":1,"j":245,"value":0.0},{"i":1,"j":246,"value":0.0},{"i":1,"j":247,"value":0.0},{"i":1,"j":248,"value":0.0},{"i":1,"j":249,"value":0.0},{"i":1,"j":250,"value":0.0},{"i":1,"j":251,"value":0.0},{"i":1,"j":252,"value":0.0},{"i":1,"j":253,"value":0.01960784313725491},{"i":1,"j":254,"value":0.03921568627450979},{"i":1,"j":255,"value":0.0},{"i":2,"j":0,"value":0.0784313725490196},{"i":2,"j":1,"value":0.0},{"i":2,"j":2,"value":0.0},{"i":2,"j":3,"value":0.0},{"i":2,"j":4,"value":0.0},{"i":2,"j":5,"value":0.0},{"i":2,"j":6,"value":0.0},{"i":2,"j":7,"value":0.0},{"i":2,"j":8,"value":0.0},{"i":2,"j":9,"value":0.019607843137254895},{"i":2,"j":10,"value":0.0},{"i":2,"j":11,"value":0.0},{"i":2,"j":12,"value":0.0},{"i":2,"j":13,"value":0.0},{"i":2,"j":14,"value":0.0},{"i":2,"j":15,"value":0.0},{"i":2,"j":16,"value":0.0},{"i":2,"j":17,"value":0.0},{"i":2,"j":18,"value":0.0},{"i":2,"j":19,"value":0.0},{"i":2,"j":20,"value":0.0},{"i":2,"j":21,"value":0.0},{"i":2,"j":22,"value":0.01960784313725489},{"i":2,"j":23,"value":0.0},{"i":2,"j":24,"value":0.019607843137254898},{"i":2,"j":25,"value":0.0},{"i":2,"j":26,"value":0.0},{"i":2,"j":27,"value":0.0},{"i":2,"j":28,"value":0.0},{"i":2,"j":29,"value":0.0},{"i":2,"j":30,"value":0.0},{"i":2,"j":31,"value":0.0},{"i":2,"j":32,"value":0.03921568627450979},{"i":2,"j":33,"value":0.0},{"i":2,"j":34,"value":0.0},{"i":2,"j":35,"value":0.0},{"i":2,"j":36,"value":0.0},{"i":2,"j":37,"value":0.0},{"i":2,"j":38,"value":0.0},{"i":2,"j":39,"value":0.07843137254901958},{"i":2,"j":40,"value":0.0},{"i":2,"j":41,"value":0.0},{"i":2,"j":42,"value":0.0},{"i":2,"j":43,"value":0.0},{"i":2,"j":44,"value":0.0},{"i":2,"j":45,"value":0.019607843137254895},{"i":2,"j":46,"value":0.0},{"i":2,"j":47,"value":0.0},{"i":2,"j":48,"value":0.0},{"i":2,"j":49,"value":0.0},{"i":2,"j":50,"value":0.01960784313725491},{"i":2,"j":51,"value":0.0},{"i":2,"j":52,"value":0.0},{"i":2,"j":53,"value":0.0},{"i":2,"j":54,"value":0.0},{"i":2,"j":55,"value":0.0},{"i":2,"j":56,"value":0.0},{"i":2,"j":57,"value":0.0},{"i":2,"j":58,"value":0.0},{"i":2,"j":59,"value":0.0},{"i":2,"j":60,"value":0.0},{"i":2,"j":61,"value":0.0},{"i":2,"j":62,"value":0.0},{"i":2,"j":63,"value":0.0},{"i":2,"j":64,"value":0.0},{"i":2,"j":65,"value":0.01960784313725491},{"i":2,"j":66,"value":0.0},{"i":2,"j":67,"value":0.0},{"i":2,"j":68,"value":0.01960784313725489},{"i":2,"j":69,"value":0.0},{"i":2,"j":70,"value":0.17647058823529413},{"i":2,"j":71,"value":0.0},{"i":2,"j":72,"value":0.0},{"i":2,"j":73,"value":0.0},{"i":2,"j":74,"value":0.0},{"i":2,"j":75,"value":0.0},{"i":2,"j":76,"value":0.0},{"i":2,"j":77,"value":0.0784313725490196},{"i":2,"j":78,"value":0.0},{"i":2,"j":79,"value":0.0},{"i":2,"j":80,"value":0.0},{"i":2,"j":81,"value":0.0},{"i":2,"j":82,"value":0.0},{"i":2,"j":83,"value":0.0},{"i":2,"j":84,"value":0.0},{"i":2,"j":85,"value":0.03921568627450979},{"i":2,"j":86,"value":0.0},{"i":2,"j":87,"value":0.0},{"i":2,"j":88,"value":0.01960784313725491},{"i":2,"j":89,"value":0.0},{"i":2,"j":90,"value":0.0},{"i":2,"j":91,"value":0.0},{"i":2,"j":92,"value":0.0},{"i":2,"j":93,"value":0.0},{"i":2,"j":94,"value":0.0},{"i":2,"j":95,"value":0.0},{"i":2,"j":96,"value":0.0},{"i":2,"j":97,"value":0.01960784313725491},{"i":2,"j":98,"value":0.0},{"i":2,"j":99,"value":0.07843137254901959},{"i":2,"j":100,"value":0.0},{"i":2,"j":101,"value":0.0},{"i":2,"j":102,"value":0.01960784313725491},{"i":2,"j":103,"value":0.0},{"i":2,"j":104,"value":0.0},{"i":2,"j":105,"value":0.0},{"i":2,"j":106,"value":0.0},{"i":2,"j":107,"value":0.019607843137254895},{"i":2,"j":108,"value":0.0},{"i":2,"j":109,"value":0.0},{"i":2,"j":110,"value":0.01960784313725489},{"i":2,"j":111,"value":0.0},{"i":2,"j":112,"value":0.0},{"i":2,"j":113,"value":0.0},{"i":2,"j":114,"value":0.01960784313725489},{"i":2,"j":115,"value":0.0},{"i":2,"j":116,"value":0.01960784313725489},{"i":2,"j":117,"value":0.0},{"i":2,"j":118,"value":0.0},{"i":2,"j":119,"value":0.01960784313725491},{"i":2,"j":120,"value":0.0},{"i":2,"j":121,"value":0.0},{"i":2,"j":122,"value":0.0},{"i":2,"j":123,"value":0.0},{"i":2,"j":124,"value":0.0},{"i":2,"j":125,"value":0.0},{"i":2,"j":126,"value":0.0},{"i":2,"j":127,"value":0.0},{"i":2,"j":128,"value":0.0},{"i":2,"j":129,"value":0.0},{"i":2,"j":130,"value":0.01960784313725491},{"i":2,"j":131,"value":0.0},{"i":2,"j":132,"value":0.0},{"i":2,"j":133,"value":0.019607843137254895},{"i":2,"j":134,"value":0.0},{"i":2,"j":135,"value":0.0},{"i":2,"j":136,"value":0.0},{"i":2,"j":137,"value":0.0},{"i":2,"j":138,"value":0.0},{"i":2,"j":139,"value":0.0},{"i":2,"j":140,"value":0.0},{"i":2,"j":141,"value":0.0},{"i":2,"j":142,"value":0.019607843137254898},{"i":2,"j":143,"value":0.0},{"i":2,"j":144,"value":0.0},{"i":2,"j":145,"value":0.0},{"i":2,"j":146,"value":0.01960784313725489},{"i":2,"j":147,"value":0.0},{"i":2,"j":148,"value":0.0},{"i":2,"j":149,"value":0.0},{"i":2,"j":150,"value":0.0},{"i":2,"j":151,"value":0.0},{"i":2,"j":152,"value":0.0},{"i":2,"j":153,"value":0.0},{"i":2,"j":154,"value":0.0},{"i":2,"j":155,"value":0.0},{"i":2,"j":156,"value":0.0},{"i":2,"j":157,"value":0.0},{"i":2,"j":158,"value":0.01960784313725491},{"i":2,"j":159,"value":0.0},{"i":2,"j":160,"value":0.0},{"i":2,"j":161,"value":0.0},{"i":2,"j":162,"value":0.0},{"i":2,"j":163,"value":0.0},{"i":2,"j":164,"value":0.0},{"i":2,"j":165,"value":0.0},{"i":2,"j":166,"value":0.0},{"i":2,"j":167,"value":0.0},{"i":2,"j":168,"value":0.0},{"i":2,"j":169,"value":0.0},{"i":2,"j":170,"value":0.0},{"i":2,"j":171,"value":0.0},{"i":2,"j":172,"value":0.0},{"i":2,"j":173,"value":0.0},{"i":2,"j":174,"value":0.0},{"i":2,"j":175,"value":0.0},{"i":2,"j":176,"value":0.0},{"i":2,"j":177,"value":0.0},{"i":2,"j":178,"value":0.0},{"i":2,"j":179,"value":0.0},{"i":2,"j":180,"value":0.0},{"i":2,"j":181,"value":0.0},{"i":2,"j":182,"value":0.0},{"i":2,"j":183,"value":0.0},{"i":2,"j":184,"value":0.0},{"i":2,"j":185,"value":0.0},{"i":2,"j":186,"value":0.0},{"i":2,"j":187,"value":0.0},{"i":2,"j":188,"value":0.0},{"i":2,"j":189,"value":0.0},{"i":2,"j":190,"value":0.0},{"i":2,"j":191,"value":0.0},{"i":2,"j":192,"value":0.0},{"i":2,"j":193,"value":0.0},{"i":2,"j":194,"value":0.0},{"i":2,"j":195,"value":0.0},{"i":2,"j":196,"value":0.0},{"i":2,"j":197,"value":0.0},{"i":2,"j":198,"value":0.0},{"i":2,"j":199,"value":0.0},{"i":2,"j":200,"value":0.0},{"i":2,"j":201,"value":0.0},{"i":2,"j":202,"value":0.0},{"i":2,"j":203,"value":0.0},{"i":2,"j":204,"value":0.0},{"i":2,"j":205,"value":0.0},{"i":2,"j":206,"value":0.0},{"i":2,"j":207,"value":0.0},{"i":2,"j":208,"value":0.0},{"i":2,"j":209,"value":0.0},{"i":2,"j":210,"value":0.0},{"i":2,"j":211,"value":0.0},{"i":2,"j":212,"value":0.0},{"i":2,"j":213,"value":0.0},{"i":2,"j":214,"value":0.0},{"i":2,"j":215,"value":0.0},{"i":2,"j":216,"value":0.0},{"i":2,"j":217,"value":0.0},{"i":2,"j":218,"value":0.0},{"i":2,"j":219,"value":0.0},{"i":2,"j":220,"value":0.0},{"i":2,"j":221,"value":0.0},{"i":2,"j":222,"value":0.0},{"i":2,"j":223,"value":0.0},{"i":2,"j":224,"value":0.0},{"i":2,"j":225,"value":0.0},{"i":2,"j":226,"value":0.0},{"i":2,"j":227,"value":0.0},{"i":2,"j":228,"value":0.0},{"i":2,"j":229,"value":0.0},{"i":2,"j":230,"value":0.0},{"i":2,"j":231,"value":0.0},{"i":2,"j":232,"value":0.0},{"i":2,"j":233,"value":0.0},{"i":2,"j":234,"value":0.0},{"i":2,"j":235,"value":0.0},{"i":2,"j":236,"value":0.0},{"i":2,"j":237,"value":0.0},{"i":2,"j":238,"value":0.0},{"i":2,"j":239,"value":0.0},{"i":2,"j":240,"value":0.0},{"i":2,"j":241,"value":0.0},{"i":2,"j":242,"value":0.0},{"i":2,"j":243,"value":0.0},{"i":2,"j":244,"value":0.0},{"i":2,"j":245,"value":0.0},{"i":2,"j":246,"value":0.0},{"i":2,"j":247,"value":0.0},{"i":2,"j":248,"value":0.0},{"i":2,"j":249,"value":0.0},{"i":2,"j":250,"value":0.0},{"i":2,"j":251,"value":0.0},{"i":2,"j":252,"value":0.0},{"i":2,"j":253,"value":0.0},{"i":2,"j":254,"value":0.03921568627450979},{"i":2,"j":255,"value":0.0},{"i":3,"j":0,"value":0.0392156862745098},{"i":3,"j":1,"value":0.13725490196078438},{"i":3,"j":2,"value":0.019607843137254895},{"i":3,"j":3,"value":0.0},{"i":3,"j":4,"value":0.0784313725490196},{"i":3,"j":5,"value":0.0},{"i":3,"j":6,"value":0.0},{"i":3,"j":7,"value":0.01960784313725489},{"i":3,"j":8,"value":0.0},{"i":3,"j":9,"value":0.0},{"i":3,"j":10,"value":0.07843137254901958},{"i":3,"j":11,"value":0.0},{"i":3,"j":12,"value":0.0},{"i":3,"j":13,"value":0.0},{"i":3,"j":14,"value":0.0},{"i":3,"j":15,"value":0.0},{"i":3,"j":16,"value":0.0},{"i":3,"j":17,"value":0.0},{"i":3,"j":18,"value":0.0},{"i":3,"j":19,"value":0.0},{"i":3,"j":20,"value":0.0},{"i":3,"j":21,"value":0.0},{"i":3,"j":22,"value":0.0},{"i":3,"j":23,"value":0.0},{"i":3,"j":24,"value":0.019607843137254898},{"i":3,"j":25,"value":0.0},{"i":3,"j":26,"value":0.0},{"i":3,"j":27,"value":0.0},{"i":3,"j":28,"value":0.0},{"i":3,"j":29,"value":0.0},{"i":3,"j":30,"value":0.0},{"i":3,"j":31,"value":0.0},{"i":3,"j":32,"value":0.0},{"i":3,"j":33,"value":0.0},{"i":3,"j":34,"value":0.0},{"i":3,"j":35,"value":0.0},{"i":3,"j":36,"value":0.0},{"i":3,"j":37,"value":0.0},{"i":3,"j":38,"value":0.0},{"i":3,"j":39,"value":0.0},{"i":3,"j":40,"value":0.0},{"i":3,"j":41,"value":0.0},{"i":3,"j":42,"value":0.0},{"i":3,"j":43,"value":0.0},{"i":3,"j":44,"value":0.0},{"i":3,"j":45,"value":0.0},{"i":3,"j":46,"value":0.0},{"i":3,"j":47,"value":0.0},{"i":3,"j":48,"value":0.0},{"i":3,"j":49,"value":0.0},{"i":3,"j":50,"value":0.0},{"i":3,"j":51,"value":0.0},{"i":3,"j":52,"value":0.0},{"i":3,"j":53,"value":0.0},{"i":3,"j":54,"value":0.019607843137254895},{"i":3,"j":55,"value":0.0},{"i":3,"j":56,"value":0.0},{"i":3,"j":57,"value":0.0},{"i":3,"j":58,"value":0.0},{"i":3,"j":59,"value":0.0},{"i":3,"j":60,"value":0.0},{"i":3,"j":61,"value":0.0},{"i":3,"j":62,"value":0.0},{"i":3,"j":63,"value":0.03921568627450981},{"i":3,"j":64,"value":0.0},{"i":3,"j":65,"value":0.019607843137254895},{"i":3,"j":66,"value":0.0},{"i":3,"j":67,"value":0.0},{"i":3,"j":68,"value":0.01960784313725491},{"i":3,"j":69,"value":0.0},{"i":3,"j":70,"value":0.01960784313725491},{"i":3,"j":71,"value":0.01960784313725491},{"i":3,"j":72,"value":0.0},{"i":3,"j":73,"value":0.0},{"i":3,"j":74,"value":0.01960784313725491},{"i":3,"j":75,"value":0.0},{"i":3,"j":76,"value":0.0},{"i":3,"j":77,"value":0.0},{"i":3,"j":78,"value":0.0},{"i":3,"j":79,"value":0.0},{"i":3,"j":80,"value":0.0784313725490196},{"i":3,"j":81,"value":0.0},{"i":3,"j":82,"value":0.0},{"i":3,"j":83,"value":0.0},{"i":3,"j":84,"value":0.0},{"i":3,"j":85,"value":0.03921568627450979},{"i":3,"j":86,"value":0.0},{"i":3,"j":87,"value":0.0},{"i":3,"j":88,"value":0.0},{"i":3,"j":89,"value":0.0},{"i":3,"j":90,"value":0.0},{"i":3,"j":91,"value":0.0},{"i":3,"j":92,"value":0.0},{"i":3,"j":93,"value":0.0},{"i":3,"j":94,"value":0.0},{"i":3,"j":95,"value":0.0},{"i":3,"j":96,"value":0.0},{"i":3,"j":97,"value":0.0},{"i":3,"j":98,"value":0.0},{"i":3,"j":99,"value":0.0},{"i":3,"j":100,"value":0.0},{"i":3,"j":101,"value":0.0},{"i":3,"j":102,"value":0.01960784313725491},{"i":3,"j":103,"value":0.0},{"i":3,"j":104,"value":0.0},{"i":3,"j":105,"value":0.03921568627450978},{"i":3,"j":106,"value":0.0},{"i":3,"j":107,"value":0.0},{"i":3,"j":108,"value":0.01960784313725491},{"i":3,"j":109,"value":0.0},{"i":3,"j":110,"value":0.0},{"i":3,"j":111,"value":0.0},{"i":3,"j":112,"value":0.0},{"i":3,"j":113,"value":0.0},{"i":3,"j":114,"value":0.019607843137254895},{"i":3,"j":115,"value":0.01960784313725489},{"i":3,"j":116,"value":0.0},{"i":3,"j":117,"value":0.058823529411764705},{"i":3,"j":118,"value":0.0},{"i":3,"j":119,"value":0.0},{"i":3,"j":120,"value":0.0},{"i":3,"j":121,"value":0.0},{"i":3,"j":122,"value":0.0},{"i":3,"j":123,"value":0.0},{"i":3,"j":124,"value":0.0},{"i":3,"j":125,"value":0.0},{"i":3,"j":126,"value":0.0},{"i":3,"j":127,"value":0.0},{"i":3,"j":128,"value":0.0},{"i":3,"j":129,"value":0.0},{"i":3,"j":130,"value":0.0},{"i":3,"j":131,"value":0.0},{"i":3,"j":132,"value":0.0},{"i":3,"j":133,"value":0.0},{"i":3,"j":134,"value":0.0},{"i":3,"j":135,"value":0.0},{"i":3,"j":136,"value":0.0},{"i":3,"j":137,"value":0.0},{"i":3,"j":138,"value":0.0},{"i":3,"j":139,"value":0.0},{"i":3,"j":140,"value":0.0},{"i":3,"j":141,"value":0.0},{"i":3,"j":142,"value":0.0},{"i":3,"j":143,"value":0.0},{"i":3,"j":144,"value":0.0},{"i":3,"j":145,"value":0.0},{"i":3,"j":146,"value":0.0},{"i":3,"j":147,"value":0.0},{"i":3,"j":148,"value":0.0},{"i":3,"j":149,"value":0.0},{"i":3,"j":150,"value":0.0},{"i":3,"j":151,"value":0.0},{"i":3,"j":152,"value":0.0},{"i":3,"j":153,"value":0.0},{"i":3,"j":154,"value":0.0},{"i":3,"j":155,"value":0.0},{"i":3,"j":156,"value":0.0},{"i":3,"j":157,"value":0.0},{"i":3,"j":158,"value":0.0},{"i":3,"j":159,"value":0.0},{"i":3,"j":160,"value":0.0},{"i":3,"j":161,"value":0.0},{"i":3,"j":162,"value":0.0},{"i":3,"j":163,"value":0.0},{"i":3,"j":164,"value":0.0},{"i":3,"j":165,"value":0.0},{"i":3,"j":166,"value":0.0},{"i":3,"j":167,"value":0.0},{"i":3,"j":168,"value":0.0},{"i":3,"j":169,"value":0.0},{"i":3,"j":170,"value":0.0},{"i":3,"j":171,"value":0.0},{"i":3,"j":172,"value":0.0},{"i":3,"j":173,"value":0.0},{"i":3,"j":174,"value":0.0},{"i":3,"j":175,"value":0.0},{"i":3,"j":176,"value":0.0},{"i":3,"j":177,"value":0.0},{"i":3,"j":178,"value":0.0},{"i":3,"j":179,"value":0.0},{"i":3,"j":180,"value":0.0},{"i":3,"j":181,"value":0.0},{"i":3,"j":182,"value":0.0},{"i":3,"j":183,"value":0.0},{"i":3,"j":184,"value":0.0},{"i":3,"j":185,"value":0.0},{"i":3,"j":186,"value":0.0},{"i":3,"j":187,"value":0.0},{"i":3,"j":188,"value":0.0},{"i":3,"j":189,"value":0.0},{"i":3,"j":190,"value":0.0},{"i":3,"j":191,"value":0.01960784313725489},{"i":3,"j":192,"value":0.019607843137254895},{"i":3,"j":193,"value":0.0},{"i":3,"j":194,"value":0.0},{"i":3,"j":195,"value":0.0},{"i":3,"j":196,"value":0.01960784313725489},{"i":3,"j":197,"value":0.0},{"i":3,"j":198,"value":0.0},{"i":3,"j":199,"value":0.01960784313725489},{"i":3,"j":200,"value":0.019607843137254895},{"i":3,"j":201,"value":0.0},{"i":3,"j":202,"value":0.0},{"i":3,"j":203,"value":0.0},{"i":3,"j":204,"value":0.0},{"i":3,"j":205,"value":0.0},{"i":3,"j":206,"value":0.0},{"i":3,"j":207,"value":0.0},{"i":3,"j":208,"value":0.0},{"i":3,"j":209,"value":0.0},{"i":3,"j":210,"value":0.0},{"i":3,"j":211,"value":0.0},{"i":3,"j":212,"value":0.0},{"i":3,"j":213,"value":0.0},{"i":3,"j":214,"value":0.0},{"i":3,"j":215,"value":0.0},{"i":3,"j":216,"value":0.0},{"i":3,"j":217,"value":0.0},{"i":3,"j":218,"value":0.0},{"i":3,"j":219,"value":0.0},{"i":3,"j":220,"value":0.0},{"i":3,"j":221,"value":0.0},{"i":3,"j":222,"value":0.0},{"i":3,"j":223,"value":0.0},{"i":3,"j":224,"value":0.0},{"i":3,"j":225,"value":0.0},{"i":3,"j":226,"value":0.0},{"i":3,"j":227,"value":0.0},{"i":3,"j":228,"value":0.0},{"i":3,"j":229,"value":0.0},{"i":3,"j":230,"value":0.0},{"i":3,"j":231,"value":0.0},{"i":3,"j":232,"value":0.0},{"i":3,"j":233,"value":0.0},{"i":3,"j":234,"value":0.0},{"i":3,"j":235,"value":0.0},{"i":3,"j":236,"value":0.0},{"i":3,"j":237,"value":0.0},{"i":3,"j":238,"value":0.0},{"i":3,"j":239,"value":0.0},{"i":3,"j":240,"value":0.0},{"i":3,"j":241,"value":0.0},{"i":3,"j":242,"value":0.0},{"i":3,"j":243,"value":0.0},{"i":3,"j":244,"value":0.0},{"i":3,"j":245,"value":0.0},{"i":3,"j":246,"value":0.0},{"i":3,"j":247,"value":0.0},{"i":3,"j":248,"value":0.0},{"i":3,"j":249,"value":0.0},{"i":3,"j":250,"value":0.0},{"i":3,"j":251,"value":0.0},{"i":3,"j":252,"value":0.0},{"i":3,"j":253,"value":0.0},{"i":3,"j":254,"value":0.03921568627450979},{"i":3,"j":255,"value":0.01960784313725491}]